bedrock_security_checker.py
bedrock_security_checker-1.0.2.dist-info/licenses/LICENSE
bedrock_security_checker-1.0.2.dist-info/METADATA
bedrock_security_checker-1.0.2.dist-info/WHEEL
bedrock_security_checker-1.0.2.dist-info/entry_points.txt
bedrock_security_checker-1.0.2.dist-info/top_level.txt
bedrock_security_checker-1.0.2.dist-info/RECORD
